{
    "sites": [
{
            "name": "иҖҒең°ж–№-line|жҳҠ",
            "type": 3,
            "api": "csp_laodifang",
            "ext": "https://raw.githubusercontent.com/kingreevice/my_xptv/refs/heads/main/js/laodifang.js"
},{
            "name": "з”өеҪұеӨ©е Ӯ-line|жҳҠ",
            "type": 3,
            "api": "csp_dytt",
            "ext": "https://raw.githubusercontent.com/kingreevice/my_xptv/refs/heads/main/js/dytt.js"
},{
            "name": "еҪұи§ҶTV-line|жҳҠ",
            "type": 3,
            "api": "csp_ysTV",
            "ext": "https://raw.githubusercontent.com/kingreevice/my_xptv/refs/heads/main/js/ysTV.js"
},{
            "name": "зҪ‘йЈһзҢ«-line|жҳҠ",
            "type": 3,
            "api": "csp_wfm",
            "ext": "https://raw.githubusercontent.com/kingreevice/my_xptv/refs/heads/main/js/wfm.js"
},{
            "name": "иҝҪеҪұзҢ«-line|жҳҠ",
            "type": 3,
            "api": "csp_zym",
            "ext": "https://raw.githubusercontent.com/kingreevice/my_xptv/refs/heads/main/js/zym.js"
},{
            "name": "е…ЁйӣҶзҪ‘-line|жҳҠ",
            "type": 3,
            "api": "csp_qjw",
            "ext": "https://raw.githubusercontent.com/kingreevice/my_xptv/refs/heads/main/js/qjw.js"
},{
            "name": "еү§иҝ·TV-line|жҳҠ",
            "type": 3,
            "api": "csp_GimyTV",
            "ext": "https://raw.githubusercontent.com/kingreevice/my_xptv/refs/heads/main/js/GimyTV.js"
},{
            "name": "зҲұеҪұеү§зҪ‘-line|жҳҠ",
            "type": 3,
            "api": "csp_aiyijw",
            "ext": "https://raw.githubusercontent.com/kingreevice/my_xptv/refs/heads/main/js/aiyjw.js"
},{
            "name": "жө·йҫҹTV-line|жҳҠ",
            "type": 3,
            "api": "csp_hgTV",
            "ext": "https://raw.githubusercontent.com/kingreevice/my_xptv/refs/heads/main/js/hgtv.js"
},{
            "name": "жЎғеӯҗеҪұи§Ҷ-line|жҳҠ",
            "type": 3,
            "api": "csp_tzsp",
            "ext": "https://raw.githubusercontent.com/kingreevice/my_xptv/refs/heads/main/js/taozi.js"
},{
            "name": "pppHub",
            "type": 3,
            "api": "csp_ppron",
            "ext": "https://raw.githubusercontent.com/kingreevice/my_xptv/refs/heads/main/js/pppPorn.js" 
},{
            "name": "жЁұиҠұеҠЁжј«-line|жҳҠ",
            "type": 3,
            "api": "csp_yhdm",
            "ext": "https://raw.githubusercontent.com/kingreevice/my_xptv/refs/heads/main/js/yhdm.js" 
},{
            "name": "е°ҸзұіUCи§Ҷйў‘-pan|жҳҠ",
            "type": 3,
            "api": "csp_js/mucpan",
            "ext": "https://raw.githubusercontent.com/kingreevice/my_xptv/refs/heads/main/js/mucpan.js" 
},{
            "name": "и§ӮеҪұзҪ‘-line-pan|жҳҠ",
            "type": 3,
            "api": "csp_js/GYING",
            "ext": "https://raw.githubusercontent.com/kingreevice/my_xptv/refs/heads/main/js/GYING-line-pan.js" 
},{
            "name": "иӮүи§Ҷйў‘",
            "type": 3,
            "api": "csp_js/rousp",
            "ext": "https://raw.githubusercontent.com/kingreevice/my_xptv/refs/heads/main/js/rousp.js" 
},{
            "name": "missav",
            "type": 3,
            "api": "csp_js/missav",
            "ext": "https://raw.githubusercontent.com/fengtangyuan/nodejs/refs/heads/main/missav.js" 
},{
            "name": "зҫҺеү§иҝ·-pan|жҳҠ",
            "type": 3,
            "api": "csp_js/meijumi",
            "ext": "https://raw.githubusercontent.com/kingreevice/my_xptv/refs/heads/main/js/meijumi.js" 
},{
            "name": "еӨ§зұіжҳҹзҗғ-line|жҳҠ",
            "type": 3,
            "api": "csp_js/dmxq",
            "ext": "https://raw.githubusercontent.com/kingreevice/my_xptv/refs/heads/main/js/dmxq.js" 
},{
            "name": "дә‘е·ў-pan|жҳҠ",
            "type": 3,
            "api": "csp_js/yunchao",
            "ext": "https://raw.githubusercontent.com/kingreevice/my_xptv/refs/heads/main/js/yunchao.js" 
},{
            "name": "ж–°и§Ҷи§ү-line|жҳҠ",
            "type": 3,
            "api": "csp_js/xsjyy",
            "ext": "https://raw.githubusercontent.com/kingreevice/my_xptv/refs/heads/main/js/xsjyy.js" 
},{
            "name": "йә»иұҶжқ‘|жҳҠ",
            "type": 3,
            "api": "csp_js/madoucun",
            "ext": "https://raw.githubusercontent.com/kingreevice/my_xptv/refs/heads/main/js/madoucun.js" 
},{
            "name": "naixxzy|жҳҠ",
            "type": 3,
            "api": "csp_js/naixxzy",
            "ext": "https://raw.githubusercontent.com/kingreevice/my_xptv/refs/heads/main/js/naixxzy.js" 
},{
            "name": "555еҪұи§Ҷ-line|жҳҠ",
            "type": 3,
            "api": "csp_js/555ys",
            "ext": "https://raw.githubusercontent.com/kingreevice/my_xptv/refs/heads/main/js/555ys.js" 
},{
            "name": "еү§йӣҶTV-line-pan|жҳҠ",
            "type": 3,
            "api": "csp_js/TV-line-pan",
            "ext": "https://raw.githubusercontent.com/kingreevice/my_xptv/refs/heads/main/js/jujiTV-line-pan.js" 
},{
            "name": "vidhub|жҳҠ",
            "type": 3,
            "api": "csp_js/vidhub",
            "ext": "https://raw.githubusercontent.com/kingreevice/my_xptv/refs/heads/main/js/vidhub.js" 
},{
            "name": "и¶Јзӣҳжҗң|жҳҠ",
            "type": 3,
            "api": "csp_js/qps",
            "ext": "https://raw.githubusercontent.com/kingreevice/my_xptv/refs/heads/main/js/qps.js" 
},{
            "name": "е°ҸиҷҺж–‘|зӣҳ",
            "type": 3,
            "api": "csp_js/huban",
            "ext": "https://raw.githubusercontent.com/kingreevice/my_xptv/refs/heads/main/js/huban.js" 
},{
            "name": "зү№дёӢйҘӯ|зӣҳ",
            "type": 3,
            "api": "csp_js/xiafan",
            "ext": "https://raw.githubusercontent.com/kingreevice/my_xptv/refs/heads/main/js/xiafan.js" 
},{
            "name": "жңЁеҒ¶|зӣҳ",
            "type": 3,
            "api": "csp_js/muou",
            "ext": "https://raw.githubusercontent.com/kingreevice/my_xptv/refs/heads/main/js/muou.js" 
},{
            "name": "е°Ҹйӣ…AList",
            "type": 3,
            "api": "csp_js/alist_xiaoya",
            "ext": "https://raw.githubusercontent.com/kingreevice/my_xptv/refs/heads/main/js/alist_xiaoya.js" 
},{
            "name": "anfuns",
            "type": 3,
            "api": "csp_js/anfuns",
            "ext": "https://raw.githubusercontent.com/kingreevice/my_xptv/refs/heads/main/js/anfuns.js" 
},{
            "name": "ж Ўй•ҝеҪұи§Ҷ",
            "type": 3,
            "api": "csp_js/xzys",
            "ext": "https://raw.githubusercontent.com/kingreevice/my_xptv/refs/heads/main/js/xzys.js" 
},{
            "name": "иҷҺж–‘/2",
            "type": 3,
            "api": "csp_js/huban",
            "ext": "https://raw.githubusercontent.com/kingreevice/my_xptv/refs/heads/main/js/huban.js" 
},{
            "name": "kanave/2",
            "type": 3,
            "api": "csp_js/kanav",
            "ext": "https://raw.githubusercontent.com/kingreevice/my_xptv/refs/heads/main/js/kanav.js" 
},{
            "name": "kanave/2",
            "type": 3,
            "api": "csp_js/kanav",
            "ext": "https://raw.githubusercontent.com/kingreevice/my_xptv/refs/heads/main/js/kanav.js" 
},
       
    ]
}
